mcp_proxy_for_aws/__init__.py
mcp_proxy_for_aws/cli.py
mcp_proxy_for_aws/client.py
mcp_proxy_for_aws/fastmcp_patch.py
mcp_proxy_for_aws/logging_config.py
mcp_proxy_for_aws/proxy.py
mcp_proxy_for_aws/server.py
mcp_proxy_for_aws/sigv4_helper.py
mcp_proxy_for_aws/utils.py
mcp_proxy_for_aws/middleware/__init__.py
mcp_proxy_for_aws/middleware/initialize_middleware.py
mcp_proxy_for_aws/middleware/tool_filter.py
mcp_proxy_for_aws-1.1.6.dist-info/METADATA
mcp_proxy_for_aws-1.1.6.dist-info/WHEEL
mcp_proxy_for_aws-1.1.6.dist-info/entry_points.txt
mcp_proxy_for_aws-1.1.6.dist-info/licenses/LICENSE
mcp_proxy_for_aws-1.1.6.dist-info/licenses/NOTICE
mcp_proxy_for_aws-1.1.6.dist-info/RECORD
