Metadata-Version: 2.4
Name: mcp-proxy-for-aws
Version: 1.1.6
Summary: MCP Proxy for AWS
Project-URL: documentation, https://github.com/aws/aws-mcp-proxy/blob/main/README.md
Project-URL: repository, https://github.com/aws/mcp-proxy-for-aws.git
Project-URL: changelog, https://github.com/aws/aws-mcp-proxy/blob/main/CHANGELOG.md
Author: Amazon Web Services, MCP Proxy for AWS
License: Apache-2.0
License-File: LICENSE
License-File: NOTICE
Classifier: License :: OSI Approved :: Apache Software License
Classifier: Operating System :: OS Independent
Classifier: Programming Language :: Python
Classifier: Programming Language :: Python :: 3
Classifier: Programming Language :: Python :: 3.10
Classifier: Programming Language :: Python :: 3.11
Classifier: Programming Language :: Python :: 3.12
Classifier: Programming Language :: Python :: 3.13
Classifier: Programming Language :: Python :: 3.14
Requires-Python: <3.15,>=3.10
Requires-Dist: boto3>=1.41.0
Requires-Dist: botocore[crt]>=1.41.0
Requires-Dist: fastmcp<2.14.1,>=2.13.1
